MANIFEST.in
README.rst
setup.cfg
setup.py
tgauth/__init__.py
tgauth/admin.py
tgauth/exceptions.py
tgauth/models.py
tgauth/tests.py
tgauth/urls.py
tgauth/views.py
tgauth.egg-info/PKG-INFO
tgauth.egg-info/SOURCES.txt
tgauth.egg-info/dependency_links.txt
tgauth.egg-info/not-zip-safe
tgauth.egg-info/requires.txt
tgauth.egg-info/top_level.txt