Metadata-Version: 1.1
Name: tgauth
Version: 1.1.1
Summary: Tgauth is a package for authentication and authorization with Telegram Messenger. its provide the Token Based Authentication.
Home-page: https://github.com/renjith-tring/tgauth
Author: Renjith S Raj
Author-email: renjith.r@tringapps.com
License: MIT
Keywords: django,oauth,telegram auth,python telegram,telegram bot auth
Platform: UNKNOWN
Classifier: Development Status :: 3 - Alpha
Classifier: Topic :: Internet
Classifier: License :: OSI Approved :: MIT License
Classifier: Intended Audience :: Developers
Classifier: Environment :: Web Environment
Classifier: Programming Language :: Python
Classifier: Programming Language :: Python :: 2.6
Classifier: Programming Language :: Python :: 2.7
Classifier: Programming Language :: Python :: 3
